MANIFEST.in
README.rst
setup.py
bin/pysmhs
config/actions.txt
config/coreconfig.txt
config/dateconfig.txt
config/tags_config.txt
pysmhs/__init__.py
pysmhs/abstracthandler.py
pysmhs/actionhandler.py
pysmhs/corehandler.py
pysmhs/datehandler.py
pysmhs/eventhandler.py
pysmhs/plchandler.py
pysmhs/webhandler.py
pysmhs.egg-info/PKG-INFO
pysmhs.egg-info/SOURCES.txt
pysmhs.egg-info/dependency_links.txt
pysmhs.egg-info/requires.txt
pysmhs.egg-info/top_level.txt
pysmhs/config/__init__.py
pysmhs/config/configobj.py
pysmhs/config/validate.py
pysmhs/handlers/__init__.py
pysmhs/www/__init__.pyc
pysmhs/www/helper_functions.js
pysmhs/www/home.svg
pysmhs/www/index.html
pysmhs/www/overview.svg
pysmhs/www/smhs.js
pysmhs/www/css/bootstrap-responsive.css
pysmhs/www/css/bootstrap-responsive.min.css
pysmhs/www/css/bootstrap.css
pysmhs/www/css/bootstrap.min.css
pysmhs/www/css/bootstrapSwitch.css
pysmhs/www/img/glyphicons-halflings-white.png
pysmhs/www/img/glyphicons-halflings.png
pysmhs/www/js/bootstrap.js
pysmhs/www/js/bootstrap.min.js
pysmhs/www/js/bootstrapSwitch.js
pysmhs/www/js/jquery-latest.js
pysmhs/www/templates/listtags_template.html
pysmhs/www/templates/monitor_template.html
test/test_datehandler.py