Metadata-Version: 1.1
Name: pysmhs
Version: 1.0.4
Summary: Smart House Control System
Home-page: http://www.pysmhs.org/
Author: Aborilov Pavel
Author-email: aborilov@gmail.com
License: UNKNOWN
Download-URL: https://github.com/aborilov/pysmhs/archive/develop.zip
Platform: UNKNOWN
